rez_quickstart/__init__.py
rez_quickstart/cli.py
rez_quickstart/packages.py
rez_quickstart_win-0.2.0.dist-info/LICENSE
rez_quickstart_win-0.2.0.dist-info/METADATA
rez_quickstart_win-0.2.0.dist-info/WHEEL
rez_quickstart_win-0.2.0.dist-info/entry_points.txt
rez_quickstart_win-0.2.0.dist-info/top_level.txt
rez_quickstart_win-0.2.0.dist-info/RECORD
