Metadata-Version: 2.1
Name: rez-quickstart-win
Version: 0.2.0
Summary: Create initial rez packages for platform, os, arch and python
Author: Thorsten Kaufmann
Classifier: Programming Language :: Python :: 3
Classifier: Operating System :: OS Independent
Classifier: Development Status :: 4 - Beta
License-File: LICENSE
Requires-Dist: click
Requires-Dist: rez >=3
